NiukeJiqiXuexiSuanfaGongchengshiMianshiTiku/README.md
NiukeJiqiXuexiSuanfaGongchengshiMianshiTiku/__init__.py
NiukeJiqiXuexiSuanfaGongchengshiMianshiTiku/__main__.py
NiukeJiqiXuexiSuanfaGongchengshiMianshiTiku/file.pdf
NiukeJiqiXuexiSuanfaGongchengshiMianshiTiku/index.html
niuke_jiqi_xuexi_suanfa_gongchengshi_mianshi_tiku-2024.3.5.0.dist-info/METADATA
niuke_jiqi_xuexi_suanfa_gongchengshi_mianshi_tiku-2024.3.5.0.dist-info/WHEEL
niuke_jiqi_xuexi_suanfa_gongchengshi_mianshi_tiku-2024.3.5.0.dist-info/entry_points.txt
niuke_jiqi_xuexi_suanfa_gongchengshi_mianshi_tiku-2024.3.5.0.dist-info/top_level.txt
niuke_jiqi_xuexi_suanfa_gongchengshi_mianshi_tiku-2024.3.5.0.dist-info/RECORD
